wekan_logstash/__init__.py
wekan_logstash/cli.py
wekan_logstash/logstash.py
wekan_logstash-0.1.6.dist-info/entry_points.txt
wekan_logstash-0.1.6.dist-info/LICENSE
wekan_logstash-0.1.6.dist-info/WHEEL
wekan_logstash-0.1.6.dist-info/METADATA
wekan_logstash-0.1.6.dist-info/RECORD
