Metadata-Version: 2.1
Name: wekan-logstash
Version: 0.1.6
Summary: Simple script that will print cards data for logstash (ELK Kibana) in JSON format
Home-page: https://github.com/fgomezotero/wekan-logstash
License: MIT
Keywords: wekan,logstash
Author: Franklin Gomez
Author-email: fgomezotero@gmail.com
Requires-Python: >=3.8
Classifier: Development Status :: 4 - Beta
Classifier: Environment :: Console
Classifier: License :: OSI Approved :: MIT License
Classifier: Programming Language :: Python :: 3
Classifier: Programming Language :: Python :: 3.10
Classifier: Programming Language :: Python :: 3.8
Classifier: Programming Language :: Python :: 3.9
Classifier: Programming Language :: Python :: Implementation
Requires-Dist: Unidecode (>=1.3.4)
Requires-Dist: click (>=8.1.3)
Requires-Dist: pymongo (>=4.1.1)
Requires-Dist: python-slugify (>=6.1.2)
Requires-Dist: requests (>=2.27.1)
Project-URL: Bug Tracker, https://github.com/fgomezotero/wekan-logstash/issues
Project-URL: Documentation, https://fgomezotero.github.io/wekan-logstash/
Project-URL: Repository, https://github.com/fgomezotero/wekan-logstash
